the_oracle.py
the_oracle-0.1.2.dist-info/METADATA
the_oracle-0.1.2.dist-info/WHEEL
the_oracle-0.1.2.dist-info/top_level.txt
the_oracle-0.1.2.dist-info/RECORD
