Metadata-Version: 2.1
Name: the-oracle
Version: 0.1.2
Summary: 🤖 Predict the stock market with AI 用AI预测股票市场
Home-page: https://github.com/ssantoshp/Oracle
Author: Santosh Passoubady
Author-email: santoshpassoubady@gmail.com
License: MIT
Platform: UNKNOWN
Requires-Dist: darts
Requires-Dist: yfinance
